{
  "8 DISPECERAT - SIGMIR": [
    { "time": "07:00", "vehicle": "BN 42 TMX" },
    { "time": "07:30", "vehicle": "BN 57 TMX" },
    { "time": "08:00", "vehicle": "BN 42 TMX" },
    { "time": "08:30", "vehicle": "BN 57 TMX" },
    { "time": "09:00", "vehicle": "BN 42 TMX" },
    { "time": "09:30", "vehicle": "BN 57 TMX" },
    { "time": "10:00", "vehicle": "BN 42 TMX" },
    { "time": "10:30", "vehicle": "BN 57 TMX" },
    { "time": "12:00", "vehicle": "BN 42 TMX" }
  ],
  "8 SIGMIR - DISPECERAT": [
    { "time": "06:00", "vehicle": "BN 42 TMX" },
    { "time": "06:30", "vehicle": "BN 57 TMX" }
  ]
}
